README.md
setup.cfg
setup.py
apollo/__init__.py
apollo/api_client.py
apollo/configuration.py
apollo/exceptions.py
apollo/model_utils.py
apollo/rest.py
apollo/apis/__init__.py
apollo/apiv2/__init__.py
apollo/apiv2/attorney_analytics_api.py
apollo/apiv2/authentication_api.py
apollo/apiv2/callback_api.py
apollo/apiv2/case_analytics_api.py
apollo/apiv2/case_docket_api.py
apollo/apiv2/case_documents_api.py
apollo/apiv2/case_export_api.py
apollo/apiv2/case_history_api.py
apollo/apiv2/case_search_api.py
apollo/apiv2/case_tracking_api.py
apollo/apiv2/case_update_api.py
apollo/apiv2/company_data_api.py
apollo/apiv2/court_availability_api.py
apollo/apiv2/court_standards_api.py
apollo/apiv2/judge_analytics_api.py
apollo/apiv2/law_firm_analytics_api.py
apollo/apiv2/pacer_api.py
apollo/apiv2/pacer_credential_api.py
apollo/apiv2/party_analytics_api.py
apollo/apiv2/usage_api.py
apollo/model/__init__.py
apollo/model/access_token_id_list_response.py
apollo/model/access_token_id_response.py
apollo/model/access_token_request.py
apollo/model/access_token_response.py
apollo/model/added_case_documents_history.py
apollo/model/added_docket_entries_history.py
apollo/model/added_hearings_history.py
apollo/model/added_judges_history.py
apollo/model/added_party_attorney_associations_history.py
apollo/model/added_related_cases_history.py
apollo/model/additional_levels.py
apollo/model/address.py
apollo/model/api_usage_response.py
apollo/model/api_usage_response_billing_cycle.py
apollo/model/area_of_law.py
apollo/model/area_of_law_response.py
apollo/model/associated_norm_attorney.py
apollo/model/associated_norm_attorney_response.py
apollo/model/associated_norm_judge.py
apollo/model/associated_norm_judge_response.py
apollo/model/associated_norm_law_firm.py
apollo/model/associated_norm_law_firm_response.py
apollo/model/associated_norm_party.py
apollo/model/associated_norm_party_response.py
apollo/model/associated_so_s_person.py
apollo/model/attorney.py
apollo/model/attorney_analytics_api.py
apollo45.egg-info/PKG-INFO
apollo45.egg-info/SOURCES.txt
apollo45.egg-info/dependency_links.txt
apollo45.egg-info/requires.txt
apollo45.egg-info/top_level.txt
